guitar_notes_update/__init__.py
guitar_notes_update/oop_guitar.py
Guitar_app-0.0.1.dist-info/METADATA
Guitar_app-0.0.1.dist-info/WHEEL
Guitar_app-0.0.1.dist-info/top_level.txt
Guitar_app-0.0.1.dist-info/RECORD
