Metadata-Version: 2.1
Name: Guitar-app
Version: 0.0.1
Summary: Guitar_app For learning guitar notes/fretboard
Home-page: UNKNOWN
Author: cliveapple265
Author-email: <cliveapple265@gmail.com>
License: UNKNOWN
Keywords: python
Platform: UNKNOWN
Classifier: Development Status :: 1 - Planning
Classifier: Intended Audience :: Developers
Classifier: Programming Language :: Python :: 3
Classifier: Operating System :: Unix
Classifier: Operating System :: MacOS :: MacOS X
Classifier: Operating System :: Microsoft :: Windows
Requires-Dist: playsound (~=1.2.2)
